{
  "root": "/mnt/home/DDN_Copy/nyu/jihanyang/yueyu/datasets/Molmo2-VideoPoint",
  "downloaded_mp4": 18265,
  "categories": {
    "action_or_event": {
      "rows": 175168,
      "unique_video": 66062,
      "covered_rows": 31425,
      "covered_unique_video": 4,
      "multi_timestamp_rows": 106572,
      "count_timestamp_mismatch_rows": 22964,
      "point_array_len_hist": {
        "1": 50965,
        "2": 32351,
        "3": 22181,
        "0": 17631,
        "4": 14608,
        "5": 9978,
        "6": 6720,
        "7": 4584
      },
      "video_sources": {
        "youtube": 175168
      },
      "note": {
        "class": "event/action count",
        "streaming": "Usually suitable. Count each event when its annotated timestamp is reached.",
        "caveat": "Preview filters corrupt/black videos and uses browser-friendly H.264 transcodes."
      },
      "samples": [
        {
          "video_id": "3BN9LL4LcoY",
          "video_url": "https://czyuyue.github.io/streamo-videopoint/videos/videopoint_h264/3BN9LL4LcoY.mp4",
          "video_path": "/mnt/home/DDN_Copy/nyu/jihanyang/yueyu/datasets/Molmo2-VideoPoint/youtube_videos/3BN9LL4LcoY.mp4",
          "question": "How many times do Roman soldiers hold spears?",
          "label": "Roman soldiers hold spears",
          "count": 5,
          "timestamp_count": 5,
          "timestamps": [
            9.5,
            19.5,
            24.5,
            41.5,
            59.5
          ],
          "raw_timestamps": [
            9.5,
            19.5,
            24.5,
            41.5,
            59.5
          ],
          "points_full": [
            [
              {
                "x": 24.84,
                "y": 37.13
              }
            ],
            [
              {
                "x": 14.77,
                "y": 83.94
              }
            ],
            [
              {
                "x": 5.19,
                "y": 84.49
              }
            ],
            [
              {
                "x": 42.05,
                "y": 23.38
              }
            ],
            [
              {
                "x": 31.69,
                "y": 68.65
              }
            ]
          ],
          "points_count": 5,
          "points_preview": [
            [
              {
                "x": 24.84,
                "y": 37.13
              }
            ],
            [
              {
                "x": 14.77,
                "y": 83.94
              }
            ],
            [
              {
                "x": 5.19,
                "y": 84.49
              }
            ]
          ],
          "points_note": "Full points are aligned one-to-one with timestamps; x/y are percentages of the decoded video frame.",
          "clip_start": 0.0,
          "clip_end": 60.0,
          "video_duration": 60.0,
          "annotator_unsure": true,
          "video_source": "youtube",
          "downloaded": true,
          "category": "action_or_event",
          "web_video_transcoded": true,
          "quality_luma": 23.176518485915494
        },
        {
          "video_id": "TXm4QHgXfxA",
          "video_url": "https://czyuyue.github.io/streamo-videopoint/videos/videopoint_h264/TXm4QHgXfxA.mp4",
          "video_path": "/mnt/home/DDN_Copy/nyu/jihanyang/yueyu/datasets/Molmo2-VideoPoint/youtube_videos/TXm4QHgXfxA.mp4",
          "question": "How many times do the security guards restrain the armed man?",
          "label": "security guards restrain the armed man",
          "count": 6,
          "timestamp_count": 6,
          "timestamps": [
            2.5,
            5.0,
            12.5,
            15.0,
            18.0,
            24.0
          ],
          "raw_timestamps": [
            2.5025,
            5.005,
            12.5125,
            15.015,
            18.018,
            24.024
          ],
          "points_full": [
            [
              {
                "x": 63.4,
                "y": 23.27
              }
            ],
            [
              {
                "x": 57.48,
                "y": 38.3
              }
            ],
            [
              {
                "x": 57.08,
                "y": 38.19
              }
            ],
            [
              {
                "x": 53.53,
                "y": 33.55
              }
            ],
            [
              {
                "x": 50.37,
                "y": 44.79
              }
            ],
            [
              {
                "x": 51.75,
                "y": 33.04
              }
            ]
          ],
          "points_count": 6,
          "points_preview": [
            [
              {
                "x": 63.4,
                "y": 23.27
              }
            ],
            [
              {
                "x": 57.48,
                "y": 38.3
              }
            ],
            [
              {
                "x": 57.08,
                "y": 38.19
              }
            ]
          ],
          "points_note": "Full points are aligned one-to-one with timestamps; x/y are percentages of the decoded video frame.",
          "clip_start": 0.0,
          "clip_end": 29.0,
          "video_duration": 29.0,
          "annotator_unsure": false,
          "video_source": "youtube",
          "downloaded": true,
          "category": "action_or_event",
          "web_video_transcoded": true,
          "quality_luma": 94.15191461267605
        },
        {
          "video_id": "6UmEHPMCZ60",
          "video_url": "https://czyuyue.github.io/streamo-videopoint/videos/videopoint_h264/6UmEHPMCZ60.mp4",
          "video_path": "/mnt/home/DDN_Copy/nyu/jihanyang/yueyu/datasets/Molmo2-VideoPoint/youtube_videos/6UmEHPMCZ60.mp4",
          "question": "How many times are different houses shown in the video?",
          "label": "different houses are shown",
          "count": 11,
          "timestamp_count": 6,
          "timestamps": [
            3.0,
            9.0,
            10.5,
            13.0,
            14.5,
            16.5
          ],
          "raw_timestamps": [
            3.0,
            9.0,
            10.5,
            13.0,
            14.5,
            16.5
          ],
          "points_full": [
            [
              {
                "x": 76.41,
                "y": 62.22
              }
            ],
            [
              {
                "x": 77.99,
                "y": 41.6
              },
              {
                "x": 74.44,
                "y": 82.9
              }
            ],
            [
              {
                "x": 74.44,
                "y": 30.85
              },
              {
                "x": 78.39,
                "y": 61.83
              }
            ],
            [
              {
                "x": 70.69,
                "y": 25.95
              },
              {
                "x": 77.6,
                "y": 61.29
              },
              {
                "x": 75.03,
                "y": 90.95
              }
            ],
            [
              {
                "x": 77.01,
                "y": 31.63
              },
              {
                "x": 77.8,
                "y": 65.2
              }
            ],
            [
              {
                "x": 77.2,
                "y": 69.16
              }
            ]
          ],
          "points_count": 6,
          "points_preview": [
            [
              {
                "x": 76.41,
                "y": 62.22
              }
            ],
            [
              {
                "x": 77.99,
                "y": 41.6
              },
              {
                "x": 74.44,
                "y": 82.9
              }
            ],
            [
              {
                "x": 74.44,
                "y": 30.85
              },
              {
                "x": 78.39,
                "y": 61.83
              }
            ]
          ],
          "points_note": "Full points are aligned one-to-one with timestamps; x/y are percentages of the decoded video frame.",
          "clip_start": 0.0,
          "clip_end": 30.0,
          "video_duration": 30.0,
          "annotator_unsure": false,
          "video_source": "youtube",
          "downloaded": true,
          "category": "action_or_event",
          "web_video_transcoded": true,
          "quality_luma": 168.390625
        },
        {
          "video_id": "3KFDn3JCdvA",
          "video_url": "https://czyuyue.github.io/streamo-videopoint/videos/videopoint_h264/3KFDn3JCdvA.mp4",
          "video_path": "/mnt/home/DDN_Copy/nyu/jihanyang/yueyu/datasets/Molmo2-VideoPoint/youtube_videos/3KFDn3JCdvA.mp4",
          "question": "How many times does the police officer speak into a microphone?",
          "label": "the police officer speaks into a microphone",
          "count": 1,
          "timestamp_count": 1,
          "timestamps": [
            42.0
          ],
          "raw_timestamps": [
            42.042
          ],
          "points_full": [
            [
              {
                "x": 56.05,
                "y": 67.95
              }
            ]
          ],
          "points_count": 1,
          "points_preview": [
            [
              {
                "x": 56.05,
                "y": 67.95
              }
            ]
          ],
          "points_note": "Full points are aligned one-to-one with timestamps; x/y are percentages of the decoded video frame.",
          "clip_start": 40.5,
          "clip_end": 48.8,
          "video_duration": 128.0,
          "annotator_unsure": false,
          "video_source": "youtube",
          "downloaded": true,
          "category": "action_or_event",
          "web_video_transcoded": true,
          "quality_luma": 85.30479166666667
        }
      ]
    },
    "object": {
      "rows": 267749,
      "unique_video": 115992,
      "covered_rows": 34885,
      "covered_unique_video": 4,
      "multi_timestamp_rows": 104549,
      "count_timestamp_mismatch_rows": 193978,
      "point_array_len_hist": {
        "1": 134738,
        "2": 41523,
        "0": 28462,
        "3": 21145,
        "4": 12515,
        "5": 7811,
        "6": 5128,
        "7": 3557
      },
      "video_sources": {
        "youtube": 267749
      },
      "note": {
        "class": "object set count",
        "streaming": "Not safe as first-seen count without extra tracking.",
        "caveat": "Often marks visible objects in one/few frames; timestamp is representative."
      },
      "samples": [
        {
          "video_id": "-tX10-uqLgE",
          "video_url": "https://czyuyue.github.io/streamo-videopoint/videos/videopoint_h264/-tX10-uqLgE.mp4",
          "video_path": "/mnt/home/DDN_Copy/nyu/jihanyang/yueyu/datasets/Molmo2-VideoPoint/youtube_videos/-tX10-uqLgE.mp4",
          "question": "How many podium poles are visible?",
          "label": "podium poles",
          "count": 2,
          "timestamp_count": 1,
          "timestamps": [
            1.0
          ],
          "raw_timestamps": [
            1.001
          ],
          "points_full": [
            [
              {
                "x": 29.03,
                "y": 85.01
              },
              {
                "x": 89.45,
                "y": 86.9
              }
            ]
          ],
          "points_count": 1,
          "points_preview": [
            [
              {
                "x": 29.03,
                "y": 85.01
              },
              {
                "x": 89.45,
                "y": 86.9
              }
            ]
          ],
          "points_note": "Full points are aligned one-to-one with timestamps; x/y are percentages of the decoded video frame.",
          "clip_start": 0.0,
          "clip_end": 58.0,
          "video_duration": 58.0,
          "annotator_unsure": false,
          "video_source": "youtube",
          "downloaded": true,
          "category": "object",
          "web_video_transcoded": true,
          "quality_luma": 155.3580985915493
        },
        {
          "video_id": "taZYrAxqVik",
          "video_url": "https://czyuyue.github.io/streamo-videopoint/videos/videopoint_h264/taZYrAxqVik.mp4",
          "video_path": "/mnt/home/DDN_Copy/nyu/jihanyang/yueyu/datasets/Molmo2-VideoPoint/youtube_videos/taZYrAxqVik.mp4",
          "question": "How many green frogs are visible?",
          "label": "green frogs",
          "count": 15,
          "timestamp_count": 5,
          "timestamps": [
            7.5,
            11.5,
            18.5,
            21.0,
            28.5
          ],
          "raw_timestamps": [
            7.5,
            11.5,
            18.5,
            21.0,
            28.5
          ],
          "points_full": [
            [
              {
                "x": 75.88,
                "y": 62.98
              },
              {
                "x": 49.52,
                "y": 61.84
              },
              {
                "x": 29.42,
                "y": 60.49
              }
            ],
            [
              {
                "x": 79.94,
                "y": 59.57
              },
              {
                "x": 27.57,
                "y": 59.47
              }
            ],
            [
              {
                "x": 54.13,
                "y": 53.98
              },
              {
                "x": 91.56,
                "y": 31.26
              },
              {
                "x": 54.49,
                "y": 33.23
              },
              {
                "x": 30.15,
                "y": 28.98
              },
              {
                "x": 14.85,
                "y": 32.2
              },
              {
                "x": 5.26,
                "y": 42.78
              }
            ],
            [
              {
                "x": 57.81,
                "y": 49.63
              }
            ],
            [
              {
                "x": 49.52,
                "y": 62.5
              },
              {
                "x": 17.43,
                "y": 79.51
              },
              {
                "x": 86.03,
                "y": 77.75
              }
            ]
          ],
          "points_count": 5,
          "points_preview": [
            [
              {
                "x": 75.88,
                "y": 62.98
              },
              {
                "x": 49.52,
                "y": 61.84
              },
              {
                "x": 29.42,
                "y": 60.49
              }
            ],
            [
              {
                "x": 79.94,
                "y": 59.57
              },
              {
                "x": 27.57,
                "y": 59.47
              }
            ],
            [
              {
                "x": 54.13,
                "y": 53.98
              },
              {
                "x": 91.56,
                "y": 31.26
              },
              {
                "x": 54.49,
                "y": 33.23
              },
              {
                "x": 30.15,
                "y": 28.98
              },
              {
                "x": 14.85,
                "y": 32.2
              },
              {
                "x": 5.26,
                "y": 42.78
              }
            ]
          ],
          "points_note": "Full points are aligned one-to-one with timestamps; x/y are percentages of the decoded video frame.",
          "clip_start": 0.0,
          "clip_end": 42.0,
          "video_duration": 42.0,
          "annotator_unsure": false,
          "video_source": "youtube",
          "downloaded": true,
          "category": "object",
          "web_video_transcoded": true,
          "quality_luma": 86.00684419014084
        },
        {
          "video_id": "-B5r696lJgM",
          "video_url": "https://czyuyue.github.io/streamo-videopoint/videos/videopoint_h264/-B5r696lJgM.mp4",
          "video_path": "/mnt/home/DDN_Copy/nyu/jihanyang/yueyu/datasets/Molmo2-VideoPoint/youtube_videos/-B5r696lJgM.mp4",
          "question": "How many phones are visible in the audience?",
          "label": "phones in the audience",
          "count": 11,
          "timestamp_count": 6,
          "timestamps": [
            13.5,
            14.0,
            21.0,
            25.0,
            29.0,
            34.5
          ],
          "raw_timestamps": [
            13.5,
            14.0,
            21.0,
            25.0,
            29.0,
            34.5
          ],
          "points_full": [
            [
              {
                "x": 13.28,
                "y": 84.47
              }
            ],
            [
              {
                "x": 43.88,
                "y": 77.03
              }
            ],
            [
              {
                "x": 36.38,
                "y": 59.14
              },
              {
                "x": 75.08,
                "y": 57.59
              },
              {
                "x": 0.84,
                "y": 59.03
              },
              {
                "x": 88.71,
                "y": 58.15
              }
            ],
            [
              {
                "x": 18.41,
                "y": 69.92
              },
              {
                "x": 83.97,
                "y": 72.25
              }
            ],
            [
              {
                "x": 71.92,
                "y": 55.59
              },
              {
                "x": 2.02,
                "y": 56.59
              }
            ],
            [
              {
                "x": 8.14,
                "y": 49.48
              }
            ]
          ],
          "points_count": 6,
          "points_preview": [
            [
              {
                "x": 13.28,
                "y": 84.47
              }
            ],
            [
              {
                "x": 43.88,
                "y": 77.03
              }
            ],
            [
              {
                "x": 36.38,
                "y": 59.14
              },
              {
                "x": 75.08,
                "y": 57.59
              },
              {
                "x": 0.84,
                "y": 59.03
              },
              {
                "x": 88.71,
                "y": 58.15
              }
            ]
          ],
          "points_note": "Full points are aligned one-to-one with timestamps; x/y are percentages of the decoded video frame.",
          "clip_start": 0.0,
          "clip_end": 46.0,
          "video_duration": 46.0,
          "annotator_unsure": false,
          "video_source": "youtube",
          "downloaded": true,
          "category": "object",
          "web_video_transcoded": true,
          "quality_luma": 127.20856073943662
        },
        {
          "video_id": "Zmb8ilbgwPg",
          "video_url": "https://czyuyue.github.io/streamo-videopoint/videos/videopoint_h264/Zmb8ilbgwPg.mp4",
          "video_path": "/mnt/home/DDN_Copy/nyu/jihanyang/yueyu/datasets/Molmo2-VideoPoint/youtube_videos/Zmb8ilbgwPg.mp4",
          "question": "How many black microphones are on the podium?",
          "label": "black microphones",
          "count": 2,
          "timestamp_count": 1,
          "timestamps": [
            0.0
          ],
          "raw_timestamps": [
            0.0
          ],
          "points_full": [
            [
              {
                "x": 64.99,
                "y": 41.67
              },
              {
                "x": 72.92,
                "y": 45.5
              }
            ]
          ],
          "points_count": 1,
          "points_preview": [
            [
              {
                "x": 64.99,
                "y": 41.67
              },
              {
                "x": 72.92,
                "y": 45.5
              }
            ]
          ],
          "points_note": "Full points are aligned one-to-one with timestamps; x/y are percentages of the decoded video frame.",
          "clip_start": 0.0,
          "clip_end": 62.0,
          "video_duration": 62.0,
          "annotator_unsure": false,
          "video_source": "youtube",
          "downloaded": true,
          "category": "object",
          "web_video_transcoded": true,
          "quality_luma": 118.33298855633802
        }
      ]
    },
    "animal": {
      "rows": 23750,
      "unique_video": 17917,
      "covered_rows": 1,
      "covered_unique_video": 0,
      "multi_timestamp_rows": 3894,
      "count_timestamp_mismatch_rows": 9961,
      "point_array_len_hist": {
        "1": 18254,
        "2": 2296,
        "0": 1602,
        "3": 737,
        "4": 355,
        "5": 195,
        "6": 105,
        "7": 53
      },
      "video_sources": {
        "MammalNet": 23750
      },
      "note": {
        "class": "object/entity set count",
        "streaming": "Not safe as first-seen count without identity tracking.",
        "caveat": "MammalNet rows mostly do not have public YouTube mapping; only valid local videos are previewed."
      },
      "samples": []
    },
    "comparative reference": {
      "rows": 48015,
      "unique_video": 48015,
      "covered_rows": 1732,
      "covered_unique_video": 4,
      "multi_timestamp_rows": 1154,
      "count_timestamp_mismatch_rows": 1575,
      "point_array_len_hist": {
        "1": 46192,
        "2": 741,
        "0": 669,
        "3": 184,
        "4": 89,
        "5": 52,
        "6": 19,
        "7": 17
      },
      "video_sources": {
        "youtube": 48015
      },
      "note": {
        "class": "single-object localization",
        "streaming": "Not a count task. Can be converted to target-visible grounding.",
        "caveat": "Mostly count=1; annotation is a target point for a comparative phrase."
      },
      "samples": [
        {
          "video_id": "p6jAexO1jrg",
          "video_url": "https://czyuyue.github.io/streamo-videopoint/videos/videopoint_h264/p6jAexO1jrg.mp4",
          "video_path": "/mnt/home/DDN_Copy/nyu/jihanyang/yueyu/datasets/Molmo2-VideoPoint/youtube_videos/p6jAexO1jrg.mp4",
          "question": "find the largest building",
          "label": "largest building",
          "count": 1,
          "timestamp_count": 1,
          "timestamps": [
            13.5
          ],
          "raw_timestamps": [
            12.96
          ],
          "points_full": [
            [
              {
                "x": 26.83,
                "y": 51.38
              }
            ]
          ],
          "points_count": 1,
          "points_preview": [
            [
              {
                "x": 26.83,
                "y": 51.38
              }
            ]
          ],
          "points_note": "Full points are aligned one-to-one with timestamps; x/y are percentages of the decoded video frame.",
          "clip_start": 0.0,
          "clip_end": 15.5,
          "video_duration": 15.5,
          "annotator_unsure": false,
          "video_source": "youtube",
          "downloaded": true,
          "category": "comparative reference",
          "web_video_transcoded": true,
          "quality_luma": 140.76952024647886
        },
        {
          "video_id": "bwOW1zShkUI",
          "video_url": "https://czyuyue.github.io/streamo-videopoint/videos/videopoint_h264/bwOW1zShkUI.mp4",
          "video_path": "/mnt/home/DDN_Copy/nyu/jihanyang/yueyu/datasets/Molmo2-VideoPoint/youtube_videos/bwOW1zShkUI.mp4",
          "question": "find the lowest hand",
          "label": "lowest hand",
          "count": 1,
          "timestamp_count": 1,
          "timestamps": [
            5.0
          ],
          "raw_timestamps": [
            5.005
          ],
          "points_full": [
            [
              {
                "x": 30.13,
                "y": 84.49
              }
            ]
          ],
          "points_count": 1,
          "points_preview": [
            [
              {
                "x": 30.13,
                "y": 84.49
              }
            ]
          ],
          "points_note": "Full points are aligned one-to-one with timestamps; x/y are percentages of the decoded video frame.",
          "clip_start": 0.0,
          "clip_end": 17.0,
          "video_duration": 17.0,
          "annotator_unsure": false,
          "video_source": "youtube",
          "downloaded": true,
          "category": "comparative reference",
          "web_video_transcoded": true,
          "quality_luma": 50.29055897887324
        },
        {
          "video_id": "0NiEpvrJlK4",
          "video_url": "https://czyuyue.github.io/streamo-videopoint/videos/videopoint_h264/0NiEpvrJlK4.mp4",
          "video_path": "/mnt/home/DDN_Copy/nyu/jihanyang/yueyu/datasets/Molmo2-VideoPoint/youtube_videos/0NiEpvrJlK4.mp4",
          "question": "find the longest potato",
          "label": "longest potato",
          "count": 1,
          "timestamp_count": 1,
          "timestamps": [
            12.5
          ],
          "raw_timestamps": [
            12.5125
          ],
          "points_full": [
            [
              {
                "x": 50.53,
                "y": 56.71
              }
            ]
          ],
          "points_count": 1,
          "points_preview": [
            [
              {
                "x": 50.53,
                "y": 56.71
              }
            ]
          ],
          "points_note": "Full points are aligned one-to-one with timestamps; x/y are percentages of the decoded video frame.",
          "clip_start": 0.0,
          "clip_end": 56.0,
          "video_duration": 56.0,
          "annotator_unsure": false,
          "video_source": "youtube",
          "downloaded": true,
          "category": "comparative reference",
          "web_video_transcoded": true,
          "quality_luma": 148.0968309859155
        },
        {
          "video_id": "0BK2YwhlFGI",
          "video_url": "https://czyuyue.github.io/streamo-videopoint/videos/videopoint_h264/0BK2YwhlFGI.mp4",
          "video_path": "/mnt/home/DDN_Copy/nyu/jihanyang/yueyu/datasets/Molmo2-VideoPoint/youtube_videos/0BK2YwhlFGI.mp4",
          "question": "find the highest red bar",
          "label": "highest red bar",
          "count": 1,
          "timestamp_count": 1,
          "timestamps": [
            2.0
          ],
          "raw_timestamps": [
            2.0
          ],
          "points_full": [
            [
              {
                "x": 60.03,
                "y": 40.74
              }
            ]
          ],
          "points_count": 1,
          "points_preview": [
            [
              {
                "x": 60.03,
                "y": 40.74
              }
            ]
          ],
          "points_note": "Full points are aligned one-to-one with timestamps; x/y are percentages of the decoded video frame.",
          "clip_start": 0.0,
          "clip_end": 24.0,
          "video_duration": 24.0,
          "annotator_unsure": false,
          "video_source": "youtube",
          "downloaded": true,
          "category": "comparative reference",
          "web_video_transcoded": true,
          "quality_luma": 87.13116197183099
        }
      ]
    },
    "indirect reference": {
      "rows": 39567,
      "unique_video": 13389,
      "covered_rows": 8354,
      "covered_unique_video": 4,
      "multi_timestamp_rows": 2409,
      "count_timestamp_mismatch_rows": 2410,
      "point_array_len_hist": {
        "1": 35627,
        "0": 1531,
        "2": 1462,
        "3": 441,
        "4": 191,
        "5": 121,
        "6": 59,
        "7": 45
      },
      "video_sources": {
        "youtube": 39567
      },
      "note": {
        "class": "single-object localization",
        "streaming": "Not a count task. Can be converted to target-visible grounding.",
        "caveat": "Requires resolving an indirect description."
      },
      "samples": [
        {
          "video_id": "JWLKBTT0l2M",
          "video_url": "https://czyuyue.github.io/streamo-videopoint/videos/videopoint_h264/JWLKBTT0l2M.mp4",
          "video_path": "/mnt/home/DDN_Copy/nyu/jihanyang/yueyu/datasets/Molmo2-VideoPoint/youtube_videos/JWLKBTT0l2M.mp4",
          "question": "find the object that stores electrical energy to start the engine",
          "label": "thing that stores electrical energy to start the engine",
          "count": 1,
          "timestamp_count": 1,
          "timestamps": [
            4.5
          ],
          "raw_timestamps": [
            4.5
          ],
          "points_full": [
            [
              {
                "x": 47.39,
                "y": 30.66
              }
            ]
          ],
          "points_count": 1,
          "points_preview": [
            [
              {
                "x": 47.39,
                "y": 30.66
              }
            ]
          ],
          "points_note": "Full points are aligned one-to-one with timestamps; x/y are percentages of the decoded video frame.",
          "clip_start": 0.5,
          "clip_end": 5.9,
          "video_duration": 154.5,
          "annotator_unsure": false,
          "video_source": "youtube",
          "downloaded": true,
          "category": "indirect reference",
          "web_video_transcoded": true,
          "quality_luma": 82.71972222222222
        },
        {
          "video_id": "LbcOiIa1lPE",
          "video_url": "https://czyuyue.github.io/streamo-videopoint/videos/videopoint_h264/LbcOiIa1lPE.mp4",
          "video_path": "/mnt/home/DDN_Copy/nyu/jihanyang/yueyu/datasets/Molmo2-VideoPoint/youtube_videos/LbcOiIa1lPE.mp4",
          "question": "find the object you would turn to open the entrance",
          "label": "thing you would turn to open the entrance",
          "count": 1,
          "timestamp_count": 1,
          "timestamps": [
            11.5
          ],
          "raw_timestamps": [
            11.5115
          ],
          "points_full": [
            [
              {
                "x": 6.32,
                "y": 41.52
              }
            ]
          ],
          "points_count": 1,
          "points_preview": [
            [
              {
                "x": 6.32,
                "y": 41.52
              }
            ]
          ],
          "points_note": "Full points are aligned one-to-one with timestamps; x/y are percentages of the decoded video frame.",
          "clip_start": 0.0,
          "clip_end": 54.5,
          "video_duration": 54.5,
          "annotator_unsure": false,
          "video_source": "youtube",
          "downloaded": true,
          "category": "indirect reference",
          "web_video_transcoded": true,
          "quality_luma": 45.35208333333333
        },
        {
          "video_id": "-BXYZwfYaXw",
          "video_url": "https://czyuyue.github.io/streamo-videopoint/videos/videopoint_h264/-BXYZwfYaXw.mp4",
          "video_path": "/mnt/home/DDN_Copy/nyu/jihanyang/yueyu/datasets/Molmo2-VideoPoint/youtube_videos/-BXYZwfYaXw.mp4",
          "question": "find the control closest to the blue flame",
          "label": "control closest to the blue flame",
          "count": 9,
          "timestamp_count": 3,
          "timestamps": [
            18.5,
            56.5,
            167.0
          ],
          "raw_timestamps": [
            18.5,
            56.5,
            167.0
          ],
          "points_full": [
            [
              {
                "x": 20.4,
                "y": 76.09
              },
              {
                "x": 19.27,
                "y": 78.76
              },
              {
                "x": 24.34,
                "y": 75.76
              }
            ],
            [
              {
                "x": 20.59,
                "y": 76.09
              },
              {
                "x": 24.72,
                "y": 72.75
              },
              {
                "x": 22.65,
                "y": 78.88
              }
            ],
            [
              {
                "x": 22.65,
                "y": 78.76
              },
              {
                "x": 19.27,
                "y": 78.09
              },
              {
                "x": 21.9,
                "y": 72.42
              }
            ]
          ],
          "points_count": 3,
          "points_preview": [
            [
              {
                "x": 20.4,
                "y": 76.09
              },
              {
                "x": 19.27,
                "y": 78.76
              },
              {
                "x": 24.34,
                "y": 75.76
              }
            ],
            [
              {
                "x": 20.59,
                "y": 76.09
              },
              {
                "x": 24.72,
                "y": 72.75
              },
              {
                "x": 22.65,
                "y": 78.88
              }
            ],
            [
              {
                "x": 22.65,
                "y": 78.76
              },
              {
                "x": 19.27,
                "y": 78.09
              },
              {
                "x": 21.9,
                "y": 72.42
              }
            ]
          ],
          "points_note": "Full points are aligned one-to-one with timestamps; x/y are percentages of the decoded video frame.",
          "clip_start": null,
          "clip_end": null,
          "video_duration": 178.5,
          "annotator_unsure": true,
          "video_source": "youtube",
          "downloaded": true,
          "category": "indirect reference",
          "web_video_transcoded": true,
          "quality_luma": 188.33909722222222
        },
        {
          "video_id": "0Z97PIxhdPU",
          "video_url": "https://czyuyue.github.io/streamo-videopoint/videos/videopoint_h264/0Z97PIxhdPU.mp4",
          "video_path": "/mnt/home/DDN_Copy/nyu/jihanyang/yueyu/datasets/Molmo2-VideoPoint/youtube_videos/0Z97PIxhdPU.mp4",
          "question": "find the object that would spill if tilted",
          "label": "thing that would spill if tilted",
          "count": 1,
          "timestamp_count": 1,
          "timestamps": [
            0.0
          ],
          "raw_timestamps": [
            0.0
          ],
          "points_full": [
            [
              {
                "x": 53.93,
                "y": 32.56
              }
            ]
          ],
          "points_count": 1,
          "points_preview": [
            [
              {
                "x": 53.93,
                "y": 32.56
              }
            ]
          ],
          "points_note": "Full points are aligned one-to-one with timestamps; x/y are percentages of the decoded video frame.",
          "clip_start": 0.0,
          "clip_end": 58.5,
          "video_duration": 58.5,
          "annotator_unsure": false,
          "video_source": "youtube",
          "downloaded": true,
          "category": "indirect reference",
          "web_video_transcoded": true,
          "quality_luma": 117.50261883802817
        }
      ]
    },
    "referring expression": {
      "rows": 60902,
      "unique_video": 20846,
      "covered_rows": 9264,
      "covered_unique_video": 4,
      "multi_timestamp_rows": 3404,
      "count_timestamp_mismatch_rows": 2783,
      "point_array_len_hist": {
        "1": 54990,
        "0": 2508,
        "2": 2268,
        "3": 509,
        "4": 230,
        "5": 128,
        "6": 93,
        "7": 46
      },
      "video_sources": {
        "youtube": 60902
      },
      "note": {
        "class": "single-object localization",
        "streaming": "Not a count task. Can be converted to target-visible grounding.",
        "caveat": "Usually one target selected by language expression."
      },
      "samples": [
        {
          "video_id": "ipWmD20rJkw",
          "video_url": "https://czyuyue.github.io/streamo-videopoint/videos/videopoint_h264/ipWmD20rJkw.mp4",
          "video_path": "/mnt/home/DDN_Copy/nyu/jihanyang/yueyu/datasets/Molmo2-VideoPoint/youtube_videos/ipWmD20rJkw.mp4",
          "question": "find the deer that grazes near the small tree with yellow leaves",
          "label": "deer that grazes near yellow-leaved tree",
          "count": 1,
          "timestamp_count": 1,
          "timestamps": [
            35.5
          ],
          "raw_timestamps": [
            35.5355
          ],
          "points_full": [
            [
              {
                "x": 56.42,
                "y": 60.87
              }
            ]
          ],
          "points_count": 1,
          "points_preview": [
            [
              {
                "x": 56.42,
                "y": 60.87
              }
            ]
          ],
          "points_note": "Full points are aligned one-to-one with timestamps; x/y are percentages of the decoded video frame.",
          "clip_start": 7.0,
          "clip_end": 36.3,
          "video_duration": 92.0,
          "annotator_unsure": false,
          "video_source": "youtube",
          "downloaded": true,
          "category": "referring expression",
          "web_video_transcoded": true,
          "quality_luma": 237.67979166666666
        },
        {
          "video_id": "0JJYdHw7Lu4",
          "video_url": "https://czyuyue.github.io/streamo-videopoint/videos/videopoint_h264/0JJYdHw7Lu4.mp4",
          "video_path": "/mnt/home/DDN_Copy/nyu/jihanyang/yueyu/datasets/Molmo2-VideoPoint/youtube_videos/0JJYdHw7Lu4.mp4",
          "question": "find the woman who bows her head and presses her temples",
          "label": "woman who bows her head and presses her temples",
          "count": 1,
          "timestamp_count": 1,
          "timestamps": [
            37.0
          ],
          "raw_timestamps": [
            37.0
          ],
          "points_full": [
            [
              {
                "x": 52.0,
                "y": 48.91
              }
            ]
          ],
          "points_count": 1,
          "points_preview": [
            [
              {
                "x": 52.0,
                "y": 48.91
              }
            ]
          ],
          "points_note": "Full points are aligned one-to-one with timestamps; x/y are percentages of the decoded video frame.",
          "clip_start": 0.0,
          "clip_end": 55.5,
          "video_duration": 55.5,
          "annotator_unsure": false,
          "video_source": "youtube",
          "downloaded": true,
          "category": "referring expression",
          "web_video_transcoded": true,
          "quality_luma": 97.49051496478873
        },
        {
          "video_id": "C4BegtvNdvg",
          "video_url": "https://czyuyue.github.io/streamo-videopoint/videos/videopoint_h264/C4BegtvNdvg.mp4",
          "video_path": "/mnt/home/DDN_Copy/nyu/jihanyang/yueyu/datasets/Molmo2-VideoPoint/youtube_videos/C4BegtvNdvg.mp4",
          "question": "find the bird that flies closest to the camera during the video",
          "label": "bird that flies closest to the camera",
          "count": 1,
          "timestamp_count": 1,
          "timestamps": [
            29.5
          ],
          "raw_timestamps": [
            29.5
          ],
          "points_full": [
            [
              {
                "x": 56.21,
                "y": 51.43
              }
            ]
          ],
          "points_count": 1,
          "points_preview": [
            [
              {
                "x": 56.21,
                "y": 51.43
              }
            ]
          ],
          "points_note": "Full points are aligned one-to-one with timestamps; x/y are percentages of the decoded video frame.",
          "clip_start": 20.0,
          "clip_end": 33.5,
          "video_duration": 66.0,
          "annotator_unsure": false,
          "video_source": "youtube",
          "downloaded": true,
          "category": "referring expression",
          "web_video_transcoded": true,
          "quality_luma": 99.69911458333333
        },
        {
          "video_id": "5scDop0TAUo",
          "video_url": "https://czyuyue.github.io/streamo-videopoint/videos/videopoint_h264/5scDop0TAUo.mp4",
          "video_path": "/mnt/home/DDN_Copy/nyu/jihanyang/yueyu/datasets/Molmo2-VideoPoint/youtube_videos/5scDop0TAUo.mp4",
          "question": "find the Godzilla whose spikes glow bright blue",
          "label": "Godzilla with glowing blue spikes",
          "count": 1,
          "timestamp_count": 1,
          "timestamps": [
            38.0
          ],
          "raw_timestamps": [
            38.0
          ],
          "points_full": [
            [
              {
                "x": 57.27,
                "y": 32.86
              }
            ]
          ],
          "points_count": 1,
          "points_preview": [
            [
              {
                "x": 57.27,
                "y": 32.86
              }
            ]
          ],
          "points_note": "Full points are aligned one-to-one with timestamps; x/y are percentages of the decoded video frame.",
          "clip_start": 7.0,
          "clip_end": 38.7,
          "video_duration": 67.0,
          "annotator_unsure": false,
          "video_source": "youtube",
          "downloaded": true,
          "category": "referring expression",
          "web_video_transcoded": true,
          "quality_luma": 63.105555555555554
        }
      ]
    },
    "spatial reference": {
      "rows": 27985,
      "unique_video": 9640,
      "covered_rows": 3298,
      "covered_unique_video": 4,
      "multi_timestamp_rows": 3841,
      "count_timestamp_mismatch_rows": 10409,
      "point_array_len_hist": {
        "1": 22701,
        "2": 2260,
        "0": 1443,
        "3": 759,
        "4": 330,
        "5": 160,
        "6": 106,
        "7": 57
      },
      "video_sources": {
        "youtube": 27985
      },
      "note": {
        "class": "single-object/part localization",
        "streaming": "Not a count task. Can be converted to spatial grounding.",
        "caveat": "Often points to an object part or spatially-defined target."
      },
      "samples": [
        {
          "video_id": "Zia24PptGPE",
          "video_url": "https://czyuyue.github.io/streamo-videopoint/videos/videopoint_h264/Zia24PptGPE.mp4",
          "video_path": "/mnt/home/DDN_Copy/nyu/jihanyang/yueyu/datasets/Molmo2-VideoPoint/youtube_videos/Zia24PptGPE.mp4",
          "question": "find the top of the Chelsea logo",
          "label": "top of Chelsea logo",
          "count": 1,
          "timestamp_count": 1,
          "timestamps": [
            0.0
          ],
          "raw_timestamps": [
            0.0
          ],
          "points_full": [
            [
              {
                "x": 9.15,
                "y": 6.55
              }
            ]
          ],
          "points_count": 1,
          "points_preview": [
            [
              {
                "x": 9.15,
                "y": 6.55
              }
            ]
          ],
          "points_note": "Full points are aligned one-to-one with timestamps; x/y are percentages of the decoded video frame.",
          "clip_start": 0.0,
          "clip_end": 2.0,
          "video_duration": 76.0,
          "annotator_unsure": false,
          "video_source": "youtube",
          "downloaded": true,
          "category": "spatial reference",
          "web_video_transcoded": true,
          "quality_luma": 122.10861111111112
        },
        {
          "video_id": "09ShmrUG6_k",
          "video_url": "https://czyuyue.github.io/streamo-videopoint/videos/videopoint_h264/09ShmrUG6_k.mp4",
          "video_path": "/mnt/home/DDN_Copy/nyu/jihanyang/yueyu/datasets/Molmo2-VideoPoint/youtube_videos/09ShmrUG6_k.mp4",
          "question": "find the coins to the right of Mario",
          "label": "coins right of Mario",
          "count": 3,
          "timestamp_count": 2,
          "timestamps": [
            13.5,
            15.5
          ],
          "raw_timestamps": [
            13.5,
            15.5
          ],
          "points_full": [
            [
              {
                "x": 77.33,
                "y": 55.52
              },
              {
                "x": 86.58,
                "y": 52.55
              }
            ],
            [
              {
                "x": 60.6,
                "y": 43.2
              }
            ]
          ],
          "points_count": 2,
          "points_preview": [
            [
              {
                "x": 77.33,
                "y": 55.52
              },
              {
                "x": 86.58,
                "y": 52.55
              }
            ],
            [
              {
                "x": 60.6,
                "y": 43.2
              }
            ]
          ],
          "points_note": "Full points are aligned one-to-one with timestamps; x/y are percentages of the decoded video frame.",
          "clip_start": 0.0,
          "clip_end": 29.0,
          "video_duration": 29.0,
          "annotator_unsure": true,
          "video_source": "youtube",
          "downloaded": true,
          "category": "spatial reference",
          "web_video_transcoded": true,
          "quality_luma": 65.744375
        },
        {
          "video_id": "0Zi1GhcaXWU",
          "video_url": "https://czyuyue.github.io/streamo-videopoint/videos/videopoint_h264/0Zi1GhcaXWU.mp4",
          "video_path": "/mnt/home/DDN_Copy/nyu/jihanyang/yueyu/datasets/Molmo2-VideoPoint/youtube_videos/0Zi1GhcaXWU.mp4",
          "question": "find the rooster in front of the window",
          "label": "rooster in front of window",
          "count": 1,
          "timestamp_count": 1,
          "timestamps": [
            6.5
          ],
          "raw_timestamps": [
            6.5065
          ],
          "points_full": [
            [
              {
                "x": 62.29,
                "y": 45.23
              }
            ]
          ],
          "points_count": 1,
          "points_preview": [
            [
              {
                "x": 62.29,
                "y": 45.23
              }
            ]
          ],
          "points_note": "Full points are aligned one-to-one with timestamps; x/y are percentages of the decoded video frame.",
          "clip_start": 0.0,
          "clip_end": 24.0,
          "video_duration": 24.0,
          "annotator_unsure": false,
          "video_source": "youtube",
          "downloaded": true,
          "category": "spatial reference",
          "web_video_transcoded": true,
          "quality_luma": 123.27119278169015
        },
        {
          "video_id": "-E9jSgjgLlk",
          "video_url": "https://czyuyue.github.io/streamo-videopoint/videos/videopoint_h264/-E9jSgjgLlk.mp4",
          "video_path": "/mnt/home/DDN_Copy/nyu/jihanyang/yueyu/datasets/Molmo2-VideoPoint/youtube_videos/-E9jSgjgLlk.mp4",
          "question": "find the center of the white plate",
          "label": "center of white plate",
          "count": 1,
          "timestamp_count": 1,
          "timestamps": [
            12.5
          ],
          "raw_timestamps": [
            12.5125
          ],
          "points_full": [
            [
              {
                "x": 55.34,
                "y": 72.18
              }
            ]
          ],
          "points_count": 1,
          "points_preview": [
            [
              {
                "x": 55.34,
                "y": 72.18
              }
            ]
          ],
          "points_note": "Full points are aligned one-to-one with timestamps; x/y are percentages of the decoded video frame.",
          "clip_start": 10.0,
          "clip_end": 19.2,
          "video_duration": 115.5,
          "annotator_unsure": true,
          "video_source": "youtube",
          "downloaded": true,
          "category": "spatial reference",
          "web_video_transcoded": true,
          "quality_luma": 120.44430555555556
        }
      ]
    },
    "anomaly": {
      "rows": 15204,
      "unique_video": 15204,
      "covered_rows": 0,
      "covered_unique_video": 4,
      "multi_timestamp_rows": 3456,
      "count_timestamp_mismatch_rows": 6134,
      "point_array_len_hist": {
        "1": 10491,
        "2": 2195,
        "0": 1257,
        "3": 726,
        "4": 311,
        "5": 100,
        "6": 52,
        "7": 26
      },
      "video_sources": {
        "generated": 15204
      },
      "note": {
        "class": "generated anomaly localization",
        "streaming": "Possible as anomaly detection, but separate from counting.",
        "caveat": "Generated videos are previewed only when non-black and decodable."
      },
      "samples": [
        {
          "video_id": "sora2-1128/temporal_and_continuity_130_v1",
          "video_url": "https://czyuyue.github.io/streamo-videopoint/videos/videopoint_h264/sora2-1128_temporal_and_continuity_130_v1.mp4",
          "video_path": "/mnt/home/DDN_Copy/nyu/jihanyang/yueyu/datasets/Molmo2-VideoPoint/generated_videos/sora2-1128/temporal_and_continuity/temporal_and_continuity_130_v1.mp4",
          "question": "find the visual anomalies in the video",
          "label": "visual anomalies",
          "count": 1,
          "timestamp_count": 1,
          "timestamps": [
            0.0
          ],
          "raw_timestamps": [
            0.0
          ],
          "points_full": [
            [
              {
                "x": 17.39,
                "y": 59.76
              }
            ]
          ],
          "points_count": 1,
          "points_preview": [
            [
              {
                "x": 17.39,
                "y": 59.76
              }
            ]
          ],
          "points_note": "Full points are aligned one-to-one with timestamps; x/y are percentages of the decoded video frame.",
          "clip_start": 0.0,
          "clip_end": 12.0,
          "video_duration": 12.0,
          "annotator_unsure": false,
          "video_source": "generated",
          "downloaded": true,
          "category": "anomaly",
          "web_video_transcoded": true,
          "quality_luma": 102.20706426056339
        },
        {
          "video_id": "sora2/temporal_and_continuity_136_v1",
          "video_url": "https://czyuyue.github.io/streamo-videopoint/videos/videopoint_h264/sora2_temporal_and_continuity_136_v1.mp4",
          "video_path": "/mnt/home/DDN_Copy/nyu/jihanyang/yueyu/datasets/Molmo2-VideoPoint/generated_videos/sora2/temporal_and_continuity/temporal_and_continuity_136_v1.mp4",
          "question": "find the visual artifacts in the video",
          "label": "visual artifacts",
          "count": 1,
          "timestamp_count": 1,
          "timestamps": [
            6.0
          ],
          "raw_timestamps": [
            6.0
          ],
          "points_full": [
            [
              {
                "x": 47.78,
                "y": 63.77
              }
            ]
          ],
          "points_count": 1,
          "points_preview": [
            [
              {
                "x": 47.78,
                "y": 63.77
              }
            ]
          ],
          "points_note": "Full points are aligned one-to-one with timestamps; x/y are percentages of the decoded video frame.",
          "clip_start": 0.0,
          "clip_end": 8.0,
          "video_duration": 8.0,
          "annotator_unsure": false,
          "video_source": "generated",
          "downloaded": true,
          "category": "anomaly",
          "web_video_transcoded": true,
          "quality_luma": 62.73222222222222
        },
        {
          "video_id": "sora2-1128/text_and_symbols_46_v1",
          "video_url": "https://czyuyue.github.io/streamo-videopoint/videos/videopoint_h264/sora2-1128_text_and_symbols_46_v1.mp4",
          "video_path": "/mnt/home/DDN_Copy/nyu/jihanyang/yueyu/datasets/Molmo2-VideoPoint/generated_videos/sora2-1128/text_and_symbols/text_and_symbols_46_v1.mp4",
          "question": "find the flaws in the video",
          "label": "flaws",
          "count": 2,
          "timestamp_count": 2,
          "timestamps": [
            2.5,
            4.5
          ],
          "raw_timestamps": [
            2.5,
            4.5
          ],
          "points_full": [
            [
              {
                "x": 44.17,
                "y": 37.5
              }
            ],
            [
              {
                "x": 37.55,
                "y": 30.22
              }
            ]
          ],
          "points_count": 2,
          "points_preview": [
            [
              {
                "x": 44.17,
                "y": 37.5
              }
            ],
            [
              {
                "x": 37.55,
                "y": 30.22
              }
            ]
          ],
          "points_note": "Full points are aligned one-to-one with timestamps; x/y are percentages of the decoded video frame.",
          "clip_start": 0.0,
          "clip_end": 8.0,
          "video_duration": 8.0,
          "annotator_unsure": false,
          "video_source": "generated",
          "downloaded": true,
          "category": "anomaly",
          "web_video_transcoded": true,
          "quality_luma": 85.90333333333334
        },
        {
          "video_id": "sora2-1128/geometry_and_camera_motion_167_v1",
          "video_url": "https://czyuyue.github.io/streamo-videopoint/videos/videopoint_h264/sora2-1128_geometry_and_camera_motion_167_v1.mp4",
          "video_path": "/mnt/home/DDN_Copy/nyu/jihanyang/yueyu/datasets/Molmo2-VideoPoint/generated_videos/sora2-1128/geometry_and_camera_motion/geometry_and_camera_motion_167_v1.mp4",
          "question": "find the distortions in the video",
          "label": "distortions",
          "count": 1,
          "timestamp_count": 1,
          "timestamps": [
            2.5
          ],
          "raw_timestamps": [
            2.5
          ],
          "points_full": [
            [
              {
                "x": 47.21,
                "y": 81.0
              }
            ]
          ],
          "points_count": 1,
          "points_preview": [
            [
              {
                "x": 47.21,
                "y": 81.0
              }
            ]
          ],
          "points_note": "Full points are aligned one-to-one with timestamps; x/y are percentages of the decoded video frame.",
          "clip_start": 0.0,
          "clip_end": 4.0,
          "video_duration": 4.0,
          "annotator_unsure": false,
          "video_source": "generated",
          "downloaded": true,
          "category": "anomaly",
          "web_video_transcoded": true,
          "quality_luma": 59.80398327464789
        }
      ]
    },
    "data": {
      "rows": 658340,
      "unique_video": 275837,
      "covered_rows": 88959,
      "covered_unique_video": 2,
      "multi_timestamp_rows": 229279,
      "count_timestamp_mismatch_rows": 250214,
      "point_array_len_hist": {
        "1": 373958,
        "2": 85096,
        "0": 55103,
        "3": 46682,
        "4": 28629,
        "5": 18545,
        "6": 12282,
        "7": 8385
      },
      "video_sources": {
        "youtube": 619386,
        "MammalNet": 23750,
        "generated": 15204
      },
      "note": {
        "class": "mixed aggregate",
        "streaming": "Do not use directly; split by category/video_source first.",
        "caveat": "Aggregate parquet containing multiple source categories; samples here are intentionally limited."
      },
      "samples": [
        {
          "video_id": "1t5wIhQ_9yQ",
          "video_url": "https://czyuyue.github.io/streamo-videopoint/videos/videopoint_h264/1t5wIhQ_9yQ.mp4",
          "video_path": "/mnt/home/DDN_Copy/nyu/jihanyang/yueyu/datasets/Molmo2-VideoPoint/youtube_videos/1t5wIhQ_9yQ.mp4",
          "question": "How many shirt buttons are visible?",
          "label": "shirt buttons",
          "count": 3,
          "timestamp_count": 1,
          "timestamps": [
            43.5
          ],
          "raw_timestamps": [
            43.5
          ],
          "points_full": [
            [
              {
                "x": 44.33,
                "y": 66.36
              },
              {
                "x": 45.07,
                "y": 74.45
              },
              {
                "x": 45.81,
                "y": 85.85
              }
            ]
          ],
          "points_count": 1,
          "points_preview": [
            [
              {
                "x": 44.33,
                "y": 66.36
              },
              {
                "x": 45.07,
                "y": 74.45
              },
              {
                "x": 45.81,
                "y": 85.85
              }
            ]
          ],
          "points_note": "Full points are aligned one-to-one with timestamps; x/y are percentages of the decoded video frame.",
          "clip_start": 0.0,
          "clip_end": 51.0,
          "video_duration": 51.0,
          "annotator_unsure": false,
          "video_source": "youtube",
          "downloaded": true,
          "category": "data",
          "web_video_transcoded": true,
          "quality_luma": 88.16996038732394
        },
        {
          "video_id": "AgG9pI0ryHU",
          "video_url": "https://czyuyue.github.io/streamo-videopoint/videos/videopoint_h264/AgG9pI0ryHU.mp4",
          "video_path": "/mnt/home/DDN_Copy/nyu/jihanyang/yueyu/datasets/Molmo2-VideoPoint/youtube_videos/AgG9pI0ryHU.mp4",
          "question": "How many houses are visible?",
          "label": "houses",
          "count": 7,
          "timestamp_count": 1,
          "timestamps": [
            7.5
          ],
          "raw_timestamps": [
            7.5075
          ],
          "points_full": [
            [
              {
                "x": 20.13,
                "y": 57.24
              },
              {
                "x": 38.65,
                "y": 51.55
              },
              {
                "x": 49.43,
                "y": 47.66
              },
              {
                "x": 65.1,
                "y": 56.04
              },
              {
                "x": 41.52,
                "y": 37.48
              },
              {
                "x": 10.19,
                "y": 34.19
              },
              {
                "x": 8.84,
                "y": 51.85
              }
            ]
          ],
          "points_count": 1,
          "points_preview": [
            [
              {
                "x": 20.13,
                "y": 57.24
              },
              {
                "x": 38.65,
                "y": 51.55
              },
              {
                "x": 49.43,
                "y": 47.66
              },
              {
                "x": 65.1,
                "y": 56.04
              },
              {
                "x": 41.52,
                "y": 37.48
              },
              {
                "x": 10.19,
                "y": 34.19
              },
              {
                "x": 8.84,
                "y": 51.85
              }
            ]
          ],
          "points_note": "Full points are aligned one-to-one with timestamps; x/y are percentages of the decoded video frame.",
          "clip_start": 0.0,
          "clip_end": 18.0,
          "video_duration": 18.0,
          "annotator_unsure": false,
          "video_source": "youtube",
          "downloaded": true,
          "category": "data",
          "web_video_transcoded": true,
          "quality_luma": 111.94708333333334
        }
      ]
    }
  }
}